ear_calculator/__init__.py
ear_calculator/ear_calculator.py
ear_calculator-0.1.1.dist-info/METADATA
ear_calculator-0.1.1.dist-info/WHEEL
ear_calculator-0.1.1.dist-info/top_level.txt
ear_calculator-0.1.1.dist-info/RECORD
